src/__init__.py
src/cli.py
src/config.py
src/main.py
src/application/__init__.py
src/application/controllers/__init__.py
src/application/controllers/game_controller.py
src/application/router/__init__.py
src/application/router/application_router.py
src/application/services/__init__.py
src/application/services/stats_service.py
src/core/__init__.py
src/core/phrase_generator.py
src/core/stats_calculator.py
src/core/word_generator.py
src/data/__init__.py
src/data/word_storage.py
src/data/resources/phrases.json
src/data/resources/words.json
src/domain/__init__.py
src/domain/config/__init__.py
src/domain/config/settings.py
src/domain/models/__init__.py
src/domain/models/game_result.py
src/domain/models/game_state.py
src/domain/models/typing_stats.py
src/domain/repositories/__init__.py
src/domain/repositories/history_repository.py
src/games/__init__.py
src/games/base_game.py
src/games/phrase_typing_game.py
src/games/random_words_game.py
src/infrastructure/__init__.py
src/infrastructure/persistence/__init__.py
src/infrastructure/persistence/json_history_repository.py
src/infrastructure/persistence/memory_history_repository.py
src/ui/__init__.py
src/ui/game_view.py
src/ui/main_app.py
src/ui/main_menu_view.py
src/ui/results_view.py
src/ui/stats_view.py
termtypr-0.4.0.dist-info/METADATA
termtypr-0.4.0.dist-info/WHEEL
termtypr-0.4.0.dist-info/entry_points.txt
termtypr-0.4.0.dist-info/licenses/LICENSE
termtypr-0.4.0.dist-info/RECORD
