Metadata-Version: 2.4
Name: termtypr
Version: 0.4.0
Summary: A Python CLI application for practicing and improving typing speed
Project-URL: Homepage, https://github.com/SteMazzO/TermTypr
Project-URL: Bug Tracker, https://github.com/SteMazzO/TermTypr/issues
Author: Stefano Mazzoleni
License-Expression: MIT
License-File: LICENSE
Keywords: cli,practice,speed,terminal,typing
Classifier: Environment :: Console
Classifier: Operating System :: OS Independent
Classifier: Programming Language :: Python :: 3
Classifier: Programming Language :: Python :: 3 :: Only
Classifier: Programming Language :: Python :: 3.9
Classifier: Programming Language :: Python :: 3.10
Classifier: Programming Language :: Python :: 3.11
Classifier: Programming Language :: Python :: 3.12
Classifier: Programming Language :: Python :: 3.13
Classifier: Programming Language :: Python :: 3.14
Classifier: Topic :: Utilities
Requires-Python: >=3.9
Requires-Dist: platformdirs>=4.1.0
Requires-Dist: plotext>=5.3.2
Requires-Dist: pydantic>=2.0.0
Requires-Dist: rich>=13.5.2
Requires-Dist: textual>=0.38.1
Requires-Dist: typer>=0.9.0
Provides-Extra: dev
Requires-Dist: pre-commit>=3.0.0; extra == 'dev'
Requires-Dist: pytest-cov>=4.0.0; extra == 'dev'
Requires-Dist: pytest>=7.0.0; extra == 'dev'
Requires-Dist: ruff>=0.2.0; extra == 'dev'
